llmproc/__init__.py
llmproc/_program_docs.py
llmproc/event_loop_mixin.py
llmproc/llm_process.py
llmproc/process_forking.py
llmproc/process_snapshot.py
llmproc/program.py
llmproc/program_config.py
llmproc/program_exec.py
llmproc/callbacks/__init__.py
llmproc/callbacks/callback_utils.py
llmproc/cli/__init__.py
llmproc/cli/__main__.py
llmproc/cli/demo.py
llmproc/cli/install_actions.py
llmproc/cli/log_utils.py
llmproc/cli/print_system_prompt.py
llmproc/cli/run.py
llmproc/common/__init__.py
llmproc/common/access_control.py
llmproc/common/constants.py
llmproc/common/context.py
llmproc/common/metadata.py
llmproc/common/results.py
llmproc/config/__init__.py
llmproc/config/mcp.py
llmproc/config/program_loader.py
llmproc/config/schema.py
llmproc/config/tool.py
llmproc/config/utils.py
llmproc/env_info/__init__.py
llmproc/env_info/builder.py
llmproc/env_info/constants.py
llmproc/file_descriptors/__init__.py
llmproc/file_descriptors/_docs_manager.py
llmproc/file_descriptors/constants.py
llmproc/file_descriptors/formatter.py
llmproc/file_descriptors/manager.py
llmproc/file_descriptors/paginator.py
llmproc/file_descriptors/references.py
llmproc/mcp_registry/LICENSE
llmproc/mcp_registry/__init__.py
llmproc/mcp_registry/compound.py
llmproc/providers/__init__.py
llmproc/providers/anthropic_process_executor.py
llmproc/providers/anthropic_utils.py
llmproc/providers/constants.py
llmproc/providers/gemini_process_executor.py
llmproc/providers/openai_process_executor.py
llmproc/providers/pricing.py
llmproc/providers/providers.py
llmproc/providers/utils.py
llmproc/tools/__init__.py
llmproc/tools/function_tools.py
llmproc/tools/registry_data.py
llmproc/tools/registry_helpers.py
llmproc/tools/tool_manager.py
llmproc/tools/tool_registry.py
llmproc/tools/builtin/__init__.py
llmproc/tools/builtin/calculator.py
llmproc/tools/builtin/fd_tools.py
llmproc/tools/builtin/fork.py
llmproc/tools/builtin/goto.py
llmproc/tools/builtin/integration.py
llmproc/tools/builtin/list_dir.py
llmproc-0.9.5.dist-info/METADATA
llmproc-0.9.5.dist-info/WHEEL
llmproc-0.9.5.dist-info/entry_points.txt
llmproc-0.9.5.dist-info/RECORD
