Metadata-Version: 2.4
Name: llmproc
Version: 0.9.5
Summary: A simple framework for LLM-powered applications
Project-URL: repository, https://github.com/cccntu/llmproc
Author-email: Jonathan Chang <31893406+cccntu@users.noreply.github.com>
License-Expression: Apache-2.0
Classifier: Development Status :: 4 - Beta
Classifier: Intended Audience :: Developers
Classifier: Operating System :: OS Independent
Classifier: Programming Language :: Python :: 3
Classifier: Programming Language :: Python :: 3.11
Classifier: Programming Language :: Python :: 3.12
Requires-Python: >=3.11
Requires-Dist: anthropic>=0.52.0
Requires-Dist: click>=8.1.8
Requires-Dist: mcp>=1.6.0
Requires-Dist: python-dotenv>=1.0.1
Requires-Dist: pyyaml>=6.0
Requires-Dist: tomli>=2.2.1
Provides-Extra: all
Requires-Dist: anthropic>=0.49.0; extra == 'all'
Requires-Dist: google-cloud-aiplatform>=1.87.0; extra == 'all'
Requires-Dist: google-genai>=1.9.0; extra == 'all'
Requires-Dist: openai>=1.70.0; extra == 'all'
Provides-Extra: anthropic
Requires-Dist: anthropic>=0.49.0; extra == 'anthropic'
Provides-Extra: gemini
Requires-Dist: google-genai>=1.9.0; extra == 'gemini'
Provides-Extra: openai
Requires-Dist: openai>=1.70.0; extra == 'openai'
Provides-Extra: vertex
Requires-Dist: google-cloud-aiplatform>=1.87.0; extra == 'vertex'
